{"./":{"url":"./","title":"Introduction","keywords":"","body":" 说明 1：目的：本次成书的目的是对CPA审计知识的再度梳理并于自身的逻辑结构，本次初步分两个阶段： 1.1：书籍知识点的重述 1.2：将知识点以图的方式建立“局部地图”——>“城市地图“——>”全局知识地图“ 2：方法：着重知识点的关键点的重述，建立”逻辑地图“ 3：项目进度管理：2017-10-27——2017-11-20 3.1：基本原理[3d] 3.2：测试流程[3d] 3.3：特殊事项考虑[3d] 3.4：完成审计工作[3d] 3.5：循环审计[3d] 3.6：内控审计[3d] 3.7：质量控制[3d] 3.8：职业道德[3d] gantt 　　　dateFormat　YYYY-MM-DD 　　　title CPA审计项目进度管理 　　　section A 　　　 　　　基本原理:active, des1, 2017-10-27, 3d 　　　测试流程:　　　　 des2, after des1, 3d 　　　特殊事项考虑:　　　　 des3, after des2 , 3d 　　　完成审计工: 　　　　 des4, after des3, 3d 　　　循环审计:　　　　 des5, after des4, 3d 　　　内控审计:　　　　 des6, after des5, 3d 　　　质量控制: 　　　　 des7, after des6 , 3d 　　　职业道德: 　　　　 des8, after des7, 3d "},"1：基本原理.html":{"url":"1：基本原理.html","title":"基本原理","keywords":"","body":"基本原理 "},"1.1：简述.html":{"url":"1.1：简述.html","title":"简述","keywords":"","body":"简述 "},"1.1.1：审计保证.html":{"url":"1.1.1：审计保证.html","title":"审计保证","keywords":"","body":"审计保证 "},"1.1.2：要素.html":{"url":"1.1.2：要素.html","title":"要素","keywords":"","body":"要素 "},"1.1.3：目标.html":{"url":"1.1.3：目标.html","title":"目标","keywords":"","body":"目标 "},"1.1.4：基本要求.html":{"url":"1.1.4：基本要求.html","title":"基本要求","keywords":"","body":"基本要求 "},"1.1.5：审计风险.html":{"url":"1.1.5：审计风险.html","title":"审计风险","keywords":"","body":"审计风险 "},"1.1.6：过程.html":{"url":"1.1.6：过程.html","title":"过程","keywords":"","body":"过程 "},"1.2：审计计划.html":{"url":"1.2：审计计划.html","title":"审计计划","keywords":"","body":"审计计划 "},"1.2.1：初步业务活动.html":{"url":"1.2.1：初步业务活动.html","title":"初步业务活动","keywords":"","body":"初步业务活动 "},"1.2.2：总体与具体.html":{"url":"1.2.2：总体与具体.html","title":"总体策略与具体计划","keywords":"","body":"总体策略与具体计划 "},"1.2.3：重要性.html":{"url":"1.2.3：重要性.html","title":"重要性","keywords":"","body":"重要性 "},"1.3：审计证据.html":{"url":"1.3：审计证据.html","title":"审计证据","keywords":"","body":"审计证据 "},"1.3.1：证据性质.html":{"url":"1.3.1：证据性质.html","title":"证据性质","keywords":"","body":"证据性质 "},"1.3.2：程序.html":{"url":"1.3.2：程序.html","title":"程序","keywords":"","body":"程序 "},"1.3.3：函证.html":{"url":"1.3.3：函证.html","title":"函证","keywords":"","body":"函证 "},"1.3.4：分析程序.html":{"url":"1.3.4：分析程序.html","title":"分析程序","keywords":"","body":"分析程序 "},"1.4：审计抽样.html":{"url":"1.4：审计抽样.html","title":"审计抽样","keywords":"","body":"审计抽样 "},"1.4.1：概述.html":{"url":"1.4.1：概述.html","title":"概述","keywords":"","body":"概述 "},"1.4.2：控制测试.html":{"url":"1.4.2：控制测试.html","title":"控制测试","keywords":"","body":"控制测试 "},"1.4.3：细节测试.html":{"url":"1.4.3：细节测试.html","title":"细节测试","keywords":"","body":"细节测试 "},"1.5：信息技术.html":{"url":"1.5：信息技术.html","title":"信息技术","keywords":"","body":"信息技术 "},"1.5.1：对内控的影响.html":{"url":"1.5.1：对内控的影响.html","title":"对内控影响","keywords":"","body":"对内控影响 "},"1.5.2：一般与应用控制.html":{"url":"1.5.2：一般与应用控制.html","title":"一般与应用控制","keywords":"","body":"一般与应用控制 "},"1.5.3：对审计的影响.html":{"url":"1.5.3：对审计的影响.html","title":"对审计影响","keywords":"","body":"对审计影响 "},"1.5.4：CAAT.html":{"url":"1.5.4：CAAT.html","title":"CAATs运用","keywords":"","body":"CAATs运用 "},"1.5.5：遇到的问题.html":{"url":"1.5.5：遇到的问题.html","title":"遇到的问题","keywords":"","body":"遇到的问题 "},"1.5.6：数据分析.html":{"url":"1.5.6：数据分析.html","title":"数据分析","keywords":"","body":"数据分析 "},"1.6：工作底稿.html":{"url":"1.6：工作底稿.html","title":"工作底稿","keywords":"","body":"工作底稿 "},"1.6.1：简述.html":{"url":"1.6.1：简述.html","title":"简述","keywords":"","body":"简述 "},"1.6.2：格式要素范围.html":{"url":"1.6.2：格式要素范围.html","title":"格式+要素+范围","keywords":"","body":"格式+要素+范围 "},"1.6.3：归档.html":{"url":"1.6.3：归档.html","title":"归档","keywords":"","body":"归档 "},"2：测试流程.html":{"url":"2：测试流程.html","title":"测试流程","keywords":"","body":"测试流程 "},"2.1：风险评估.html":{"url":"2.1：风险评估.html","title":"风险评估","keywords":"","body":"风险评估 "},"2.1.1：识别评估.html":{"url":"2.1.1：识别评估.html","title":"识别评估","keywords":"","body":"识别评估 "},"2.1.2：评估程序.html":{"url":"2.1.2：评估程序.html","title":"评估程序","keywords":"","body":"评估程序 "},"2.1.3：了解环境.html":{"url":"2.1.3：了解环境.html","title":"了解环境","keywords":"","body":"了解环境 "},"2.1.4：了解内控.html":{"url":"2.1.4：了解内控.html","title":"了解内控","keywords":"","body":"了解内控 "},"2.1.5：评估风险.html":{"url":"2.1.5：评估风险.html","title":"评估风险","keywords":"","body":"评估风险 "},"2.2：风险应对.html":{"url":"2.2：风险应对.html","title":"风险应对","keywords":"","body":"风险应对 "},"2.2.1：报表层次应对.html":{"url":"2.2.1：报表层次应对.html","title":"报表层次应对","keywords":"","body":"报表层次应对 "},"2.2.2：认定层次应对.html":{"url":"2.2.2：认定层次应对.html","title":"认定层次应对","keywords":"","body":"认定层次应对 "},"2.2.3：控制测试.html":{"url":"2.2.3：控制测试.html","title":"控制测试","keywords":"","body":"控制测试 "},"2.2.4：实质性分析.html":{"url":"2.2.4：实质性分析.html","title":"实质性分析","keywords":"","body":"实质性分析 "},"3：特殊事项考虑.html":{"url":"3：特殊事项考虑.html","title":"特殊事项考虑","keywords":"","body":"特殊事项考虑 "},"3.1：舞弊与法律.html":{"url":"3.1：舞弊与法律.html","title":"舞弊与法律","keywords":"","body":"舞弊与法律 "},"3.1.1：舞弊责任.html":{"url":"3.1.1：舞弊责任.html","title":"舞弊责任","keywords":"","body":"舞弊责任 "},"3.1.2：法律考虑.html":{"url":"3.1.2：法律考虑.html","title":"法律考虑","keywords":"","body":"法律考虑 "},"3.2：审计沟通.html":{"url":"3.2：审计沟通.html","title":"审计沟通","keywords":"","body":"审计沟通 "},"3.2.1：CPA与治理层.html":{"url":"3.2.1：CPA与治理层.html","title":"CPA与治理层","keywords":"","body":"CPA与治理层 "},"3.2.2：前后任.html":{"url":"3.2.2：前后任.html","title":"前后任","keywords":"","body":"前后任 "},"3.3：利用他人.html":{"url":"3.3：利用他人.html","title":"利用他人","keywords":"","body":"利用他人 "},"3.3.1：利用内审.html":{"url":"3.3.1：利用内审.html","title":"利用内审","keywords":"","body":"利用内审 "},"3.3.2：利用专家.html":{"url":"3.3.2：利用专家.html","title":"利用专家","keywords":"","body":"利用专家 "},"3.4：集团审计.html":{"url":"3.4：集团审计.html","title":"集团审计","keywords":"","body":"集团审计 "},"3.4.1：有关概念.html":{"url":"3.4.1：有关概念.html","title":"有关概念","keywords":"","body":"有关概念 "},"3.4.2：责任与目标.html":{"url":"3.4.2：责任与目标.html","title":"责任与目标","keywords":"","body":"责任与目标 "},"3.4.3：承接与保持.html":{"url":"3.4.3：承接与保持.html","title":"承接与保持","keywords":"","body":"承接与保持 "},"3.4.4：了解环境.html":{"url":"3.4.4：了解环境.html","title":"了解环境","keywords":"","body":"了解环境 "},"3.4.5：组成部分CPA.html":{"url":"3.4.5：组成部分CPA.html","title":"了解组成部分CPA","keywords":"","body":"了解组成部分CPA "},"3.4.6：重要性.html":{"url":"3.4.6：重要性.html","title":"重要性","keywords":"","body":"重要性 "},"3.4.7：风险应对.html":{"url":"3.4.7：风险应对.html","title":"风险应对","keywords":"","body":"风险应对 "},"3.4.8：合并过程.html":{"url":"3.4.8：合并过程.html","title":"合并过程","keywords":"","body":"合并过程 "},"3.4.9：与组成部分CPA沟通.html":{"url":"3.4.9：与组成部分CPA沟通.html","title":"与组成部分CPA沟通","keywords":"","body":"与组成部分CPA沟通 "},"3.4.10：评价证据.html":{"url":"3.4.10：评价证据.html","title":"评价证据","keywords":"","body":"评价证据 "},"3.4.11：与管理层治理层沟通.html":{"url":"3.4.11：与管理层治理层沟通.html","title":"与管理层治理层沟通","keywords":"","body":"与管理层治理层沟通 "},"3.5：其他特殊考虑.html":{"url":"3.5：其他特殊考虑.html","title":"其他特殊考虑","keywords":"","body":"其他特殊考虑 "},"3.5.1：会计估计.html":{"url":"3.5.1：会计估计.html","title":"会计估计","keywords":"","body":"会计估计 "},"3.5.2：关联方.html":{"url":"3.5.2：关联方.html","title":"关联方","keywords":"","body":"关联方 "},"3.5.3：持续性假设.html":{"url":"3.5.3：持续性假设.html","title":"持续性假设","keywords":"","body":"持续性假设 "},"3.5.4：首次期初审计.html":{"url":"3.5.4：首次期初审计.html","title":"首次期初审计","keywords":"","body":"首次期初审计 "},"4：完成审计工作.html":{"url":"4：完成审计工作.html","title":"完成审计工作","keywords":"","body":"完成审计工作 "},"4.1：完成工作.html":{"url":"4.1：完成工作.html","title":"完成工作","keywords":"","body":"完成工作 "},"4.1.1：简述.html":{"url":"4.1.1：简述.html","title":"简述","keywords":"","body":"简述 "},"4.1.2：期后事项.html":{"url":"4.1.2：期后事项.html","title":"期后事项","keywords":"","body":"期后事项 "},"4.1.3：书面申明.html":{"url":"4.1.3：书面申明.html","title":"书面申明","keywords":"","body":"书面申明 "},"4.2：审计报告.html":{"url":"4.2：审计报告.html","title":"审计报告","keywords":"","body":"审计报告 "},"4.2.1：简述.html":{"url":"4.2.1：简述.html","title":"简述","keywords":"","body":"简述 "},"4.2.2：审计意见.html":{"url":"4.2.2：审计意见.html","title":"审计意见","keywords":"","body":"审计意见 "},"4.2.3：基本内容.html":{"url":"4.2.3：基本内容.html","title":"基本内容","keywords":"","body":"基本内容 "},"4.2.4：关键审计事项.html":{"url":"4.2.4：关键审计事项.html","title":"关键审计事项","keywords":"","body":"关键审计事项 "},"4.2.5：非无保留意见.html":{"url":"4.2.5：非无保留意见.html","title":"非无保留意见","keywords":"","body":"非无保留意见 "},"4.2.6：强调与其他事项.html":{"url":"4.2.6：强调与其他事项.html","title":"强调与其他事项","keywords":"","body":"强调与其他事项 "},"4.2.7：比较信息.html":{"url":"4.2.7：比较信息.html","title":"比较信息","keywords":"","body":"比较信息 "},"4.2.8：CPA其他责任.html":{"url":"4.2.8：CPA其他责任.html","title":"CPA其他责任","keywords":"","body":"CPA其他责任 "},"5：循环审计.html":{"url":"5：循环审计.html","title":"循环审计","keywords":"","body":"循环审计 "},"5.1：销售收款.html":{"url":"5.1：销售收款.html","title":"销售收款","keywords":"","body":"销售收款 "},"5.1.1：特点.html":{"url":"5.1.1：特点.html","title":"特点","keywords":"","body":"特点 "},"5.1.2：活动与控制.html":{"url":"5.1.2：活动与控制.html","title":"活动与控制","keywords":"","body":"活动与控制 "},"5.1.3：风险评估.html":{"url":"5.1.3：风险评估.html","title":"风险评估","keywords":"","body":"风险评估 "},"5.1.4：内控.html":{"url":"5.1.4：内控.html","title":"内控","keywords":"","body":"内控 "},"5.1.5：实质性程序.html":{"url":"5.1.5：实质性程序.html","title":"实质性程序","keywords":"","body":"实质性程序 "},"5.2：采购付款.html":{"url":"5.2：采购付款.html","title":"采购付款","keywords":"","body":"采购付款 "},"5.2.1：特点.html":{"url":"5.2.1：特点.html","title":"特点","keywords":"","body":"特点 "},"5.2.2：活动与控制.html":{"url":"5.2.2：活动与控制.html","title":"活动与控制","keywords":"","body":"活动与控制 "},"5.2.3：错报风险.html":{"url":"5.2.3：错报风险.html","title":"错报风险","keywords":"","body":"错报风险 "},"5.2.4：内控.html":{"url":"5.2.4：内控.html","title":"内控","keywords":"","body":"内控 "},"5.2.5：实质性程序.html":{"url":"5.2.5：实质性程序.html","title":"实质性程序","keywords":"","body":"实质性程序 "},"5.3：生产存货.html":{"url":"5.3：生产存货.html","title":"生产存货","keywords":"","body":"生产存货 "},"5.3.1：特点.html":{"url":"5.3.1：特点.html","title":"特点","keywords":"","body":"特点 "},"5.3.2：活动与控制.html":{"url":"5.3.2：活动与控制.html","title":"活动与控制","keywords":"","body":"活动与控制 "},"5.3.3：错报风险.html":{"url":"5.3.3：错报风险.html","title":"错报风险","keywords":"","body":"错报风险 "},"5.3.4：控制测试.html":{"url":"5.3.4：控制测试.html","title":"控制测试","keywords":"","body":"控制测试 "},"5.3.5：实质性程序.html":{"url":"5.3.5：实质性程序.html","title":"实质性程序","keywords":"","body":"实质性程序 "},"5.4：货币.html":{"url":"5.4：货币.html","title":"货币","keywords":"","body":"货币 "},"5.4.1：简述.html":{"url":"5.4.1：简述.html","title":"简述","keywords":"","body":"简述 "},"5.4.2：错报风险.html":{"url":"5.4.2：错报风险.html","title":"错报风险","keywords":"","body":"错报风险 "},"5.4.3：内控.html":{"url":"5.4.3：内控.html","title":"内控","keywords":"","body":"内控 "},"5.4.4：实质性程序.html":{"url":"5.4.4：实质性程序.html","title":"实质性程序","keywords":"","body":"实质性程序 "},"6：内控审计.html":{"url":"6：内控审计.html","title":"内控审计","keywords":"","body":"内控审计 "},"6.1：内控审计.html":{"url":"6.1：内控审计.html","title":"内控审计","keywords":"","body":"内控审计 "},"6.1.1：简述.html":{"url":"6.1.1：简述.html","title":"简述","keywords":"","body":"简述 "},"6.1.2：计划审计工作.html":{"url":"6.1.2：计划审计工作.html","title":"计划审计工作","keywords":"","body":"计划审计工作 "},"6.1.3：自上而下.html":{"url":"6.1.3：自上而下.html","title":"自上而下","keywords":"","body":"自上而下 "},"6.1.4：内控测试.html":{"url":"6.1.4：内控测试.html","title":"内控测试","keywords":"","body":"内控测试 "},"6.1.5：企业层面测试.html":{"url":"6.1.5：企业层面测试.html","title":"企业层面测试","keywords":"","body":"企业层面测试 "},"6.1.6：交易层面测试.html":{"url":"6.1.6：交易层面测试.html","title":"交易层面测试","keywords":"","body":"交易层面测试 "},"6.1.7：信息系统评价.html":{"url":"6.1.7：信息系统评价.html","title":"信息系统评价","keywords":"","body":"信息系统评价 "},"6.1.8：内控缺陷评价.html":{"url":"6.1.8：内控缺陷评价.html","title":"内控缺陷评价","keywords":"","body":"内控缺陷评价 "},"6.1.9：出具报告.html":{"url":"6.1.9：出具报告.html","title":"出具报告","keywords":"","body":"出具报告 "},"7：质量控制.html":{"url":"7：质量控制.html","title":"质量控制","keywords":"","body":"质量控制 "},"7.1：质量控制.html":{"url":"7.1：质量控制.html","title":"质量控制","keywords":"","body":"质量控制 "},"7.1.1：目标与领导责任.html":{"url":"7.1.1：目标与领导责任.html","title":"目标与领导责任","keywords":"","body":"目标与领导责任 "},"7.1.2：职业道德要求.html":{"url":"7.1.2：职业道德要求.html","title":"职业道德要求","keywords":"","body":"职业道德要求 "},"7.1.3：客户关系与承接.html":{"url":"7.1.3：客户关系与承接.html","title":"客户关系与承接","keywords":"","body":"客户关系与承接 "},"7.1.4：人力资源.html":{"url":"7.1.4：人力资源.html","title":"人力资源","keywords":"","body":"人力资源 "},"7.1.5：业务执行.html":{"url":"7.1.5：业务执行.html","title":"业务执行","keywords":"","body":"业务执行 "},"7.1.6：监控.html":{"url":"7.1.6：监控.html","title":"监控","keywords":"","body":"监控 "},"8：职业道德.html":{"url":"8：职业道德.html","title":"职业道德","keywords":"","body":"职业道德 "},"8.1：原则与框架.html":{"url":"8.1：原则与框架.html","title":"原则与框架","keywords":"","body":"原则与框架 "},"8.1.1：原则.html":{"url":"8.1.1：原则.html","title":"原则","keywords":"","body":"原则 "},"8.1.2：框架.html":{"url":"8.1.2：框架.html","title":"框架","keywords":"","body":"框架 "},"8.1.3：CPA具体应用.html":{"url":"8.1.3：CPA具体应用.html","title":"CPA具体应用","keywords":"","body":"CPA具体应用 "},"8.1.4：非执业会员.html":{"url":"8.1.4：非执业会员.html","title":"非执业会员应用","keywords":"","body":"非执业会员应用 "},"8.2：独立性要求.html":{"url":"8.2：独立性要求.html","title":"独立性要求","keywords":"","body":"独立性要求 "},"8.2.1：基本要求.html":{"url":"8.2.1：基本要求.html","title":"基本要求","keywords":"","body":"基本要求 "},"8.2.2：经济利益.html":{"url":"8.2.2：经济利益.html","title":"经济利益","keywords":"","body":"经济利益 "},"8.2.3：贷款担保.html":{"url":"8.2.3：贷款担保.html","title":"贷款担保","keywords":"","body":"贷款担保 "},"8.2.4：人员交流.html":{"url":"8.2.4：人员交流.html","title":"人员交流","keywords":"","body":"人员交流 "},"8.2.5：长期关系.html":{"url":"8.2.5：长期关系.html","title":"长期关系","keywords":"","body":"长期关系 "},"8.2.6：非鉴证服务.html":{"url":"8.2.6：非鉴证服务.html","title":"非鉴证服务","keywords":"","body":"非鉴证服务 "},"8.2.7：收费.html":{"url":"8.2.7：收费.html","title":"收费","keywords":"","body":"收费 "},"8.2.8：其他.html":{"url":"8.2.8：其他.html","title":"其他","keywords":"","body":"其他 "}}